.coveragerc
LICENSE
MANIFEST.in
README.md
dev_requirements.txt
requirements.txt
setup.cfg
setup.py
versioneer.py
csirtg_spamhaus/__init__.py
csirtg_spamhaus/_version.py
csirtg_spamhaus/constants.py
csirtg_spamhaus.egg-info/PKG-INFO
csirtg_spamhaus.egg-info/SOURCES.txt
csirtg_spamhaus.egg-info/dependency_links.txt
csirtg_spamhaus.egg-info/entry_points.txt
csirtg_spamhaus.egg-info/requires.txt
csirtg_spamhaus.egg-info/top_level.txt
test/test_basics.py