Metadata-Version: 1.1
Name: csirtg-spamhaus
Version: 0.1
Summary: CSIRTG Spamhaus Utility
Home-page: https://github.com/csirtgadgets/csirtg-spamhaus
Author: Wes Young
Author-email: wes@csirtgadgets.com
License: MPL2
Keywords: security
Platform: UNKNOWN
Classifier: Programming Language :: Python
